{
  "metadata": {
    "stage": "token_diag",
    "input_split": "train_only",
    "train_csv": "/home/pak/Documents/src_baocao/01_split/train_raw.csv",
    "K": 512,
    "effective_num_bins": 512,
    "n_rows": 46876,
    "n_features": 55,
    "excluded_target_cols": [
      "label_L1",
      "label_L2",
      "label_L3",
      "Class",
      "Category"
    ],
    "drop_cols": [],
    "token_rule": "train-only MinMax; z=(x-min)/(max-min); clipped [0,1]; token=floor(K*z); clipped [0,K-1]; exactly K bins",
    "core_metrics": {
      "preserve_ratio": "bins_used / min(raw_unique, K)",
      "compression_factor": "raw_unique / max(bins_used, 1)",
      "entropy_norm": "-sum(p_i log p_i) / log(bins_used), computed over used token bins only"
    },
    "decision_rule": {
      "drop": "raw_unique <= 1",
      "transform": "preserve_ratio < preserve_threshold OR compression_factor > compression_threshold OR (raw_unique > K AND entropy_norm < entropy_threshold)",
      "keep": "otherwise"
    },
    "thresholds": {
      "preserve_threshold": 0.95,
      "compression_threshold": 8.0,
      "entropy_threshold": 0.75,
      "entropy_trigger_requires_raw_unique_gt_K": true
    },
    "decision_counts": {
      "keep": 26,
      "transform": 26,
      "drop": 3
    }
  },
  "features": [
    {
      "feature": "pslist.nproc",
      "n": 46876,
      "K": 512,
      "effective_num_bins": 512,
      "raw": {
        "train_min": 21.0,
        "train_max": 240.0,
        "train_range": 219.0,
        "num_unique": 105,
        "zero_ratio": 0.0,
        "is_constant": false
      },
      "token": {
        "num_tokens_used": 105,
        "bins_used": 105,
        "possible_unique": 105,
        "preserve_ratio": 1.0,
        "unique_preserve_ratio": 1.0,
        "compression_factor": 1.0,
        "entropy_norm": 0.5634949111344502,
        "quantiles": {
          "min": 0,
          "q10": 37,
          "q25": 44,
          "q75": 51,
          "q90": 56,
          "max": 511
        }
      },
      "decision": {
        "label": "keep",
        "reasons": [
          "metrics_within_thresholds"
        ],
        "thresholds": {
          "preserve_threshold": 0.95,
          "compression_threshold": 8.0,
          "entropy_threshold": 0.75,
          "entropy_trigger_requires_raw_unique_gt_K": true
        }
      }
    },
    {
      "feature": "pslist.nppid",
      "n": 46876,
      "K": 512,
      "effective_num_bins": 512,
      "raw": {
        "train_min": 8.0,
        "train_max": 66.0,
        "train_range": 58.0,
        "num_unique": 48,
        "zero_ratio": 0.0,
        "is_constant": false
      },
      "token": {
        "num_tokens_used": 48,
        "bins_used": 48,
        "possible_unique": 48,
        "preserve_ratio": 1.0,
        "unique_preserve_ratio": 1.0,
        "compression_factor": 1.0,
        "entropy_norm": 0.5190073123050564,
        "quantiles": {
          "min": 0,
          "q10": 35,
          "q25": 35,
          "q75": 70,
          "q90": 79,
          "max": 511
        }
      },
      "decision": {
        "label": "keep",
        "reasons": [
          "metrics_within_thresholds"
        ],
        "thresholds": {
          "preserve_threshold": 0.95,
          "compression_threshold": 8.0,
          "entropy_threshold": 0.75,
          "entropy_trigger_requires_raw_unique_gt_K": true
        }
      }
    },
    {
      "feature": "pslist.avg_threads",
      "n": 46876,
      "K": 512,
      "effective_num_bins": 512,
      "raw": {
        "train_min": 1.65,
        "train_max": 16.81818182,
        "train_range": 15.16818182,
        "num_unique": 22592,
        "zero_ratio": 0.0,
        "is_constant": false
      },
      "token": {
        "num_tokens_used": 386,
        "bins_used": 386,
        "possible_unique": 512,
        "preserve_ratio": 0.75390625,
        "unique_preserve_ratio": 0.75390625,
        "compression_factor": 58.52849740932643,
        "entropy_norm": 0.8432098810308458,
        "quantiles": {
          "min": 0,
          "q10": 266,
          "q25": 280,
          "q75": 378,
          "q90": 395,
          "max": 511
        }
      },
      "decision": {
        "label": "transform",
        "reasons": [
          "low_preserve_ratio",
          "high_compression_factor"
        ],
        "thresholds": {
          "preserve_threshold": 0.95,
          "compression_threshold": 8.0,
          "entropy_threshold": 0.75,
          "entropy_trigger_requires_raw_unique_gt_K": true
        }
      }
    },
    {
      "feature": "pslist.nprocs64bit",
      "n": 46876,
      "K": 512,
      "effective_num_bins": 512,
      "raw": {
        "train_min": 0.0,
        "train_max": 0.0,
        "train_range": 0.0,
        "num_unique": 1,
        "zero_ratio": 1.0,
        "is_constant": true
      },
      "token": {
        "num_tokens_used": 1,
        "bins_used": 1,
        "possible_unique": 1,
        "preserve_ratio": 1.0,
        "unique_preserve_ratio": 1.0,
        "compression_factor": 1.0,
        "entropy_norm": 1.0,
        "quantiles": {
          "min": 0,
          "q10": 0,
          "q25": 0,
          "q75": 0,
          "q90": 0,
          "max": 0
        }
      },
      "decision": {
        "label": "drop",
        "reasons": [
          "constant_feature"
        ],
        "thresholds": {
          "preserve_threshold": 0.95,
          "compression_threshold": 8.0,
          "entropy_threshold": 0.75,
          "entropy_trigger_requires_raw_unique_gt_K": true
        }
      }
    },
    {
      "feature": "pslist.avg_handlers",
      "n": 46876,
      "K": 512,
      "effective_num_bins": 512,
      "raw": {
        "train_min": 34.9625,
        "train_max": 1174.536585,
        "train_range": 1139.574085,
        "num_unique": 30009,
        "zero_ratio": 0.0,
        "is_constant": false
      },
      "token": {
        "num_tokens_used": 209,
        "bins_used": 209,
        "possible_unique": 512,
        "preserve_ratio": 0.408203125,
        "unique_preserve_ratio": 0.408203125,
        "compression_factor": 143.58373205741626,
        "entropy_norm": 0.7057225544413013,
        "quantiles": {
          "min": 0,
          "q10": 74,
          "q25": 78,
          "q75": 114,
          "q90": 120,
          "max": 511
        }
      },
      "decision": {
        "label": "transform",
        "reasons": [
          "low_preserve_ratio",
          "high_compression_factor",
          "low_entropy_norm_high_unique"
        ],
        "thresholds": {
          "preserve_threshold": 0.95,
          "compression_threshold": 8.0,
          "entropy_threshold": 0.75,
          "entropy_trigger_requires_raw_unique_gt_K": true
        }
      }
    },
    {
      "feature": "dlllist.ndlls",
      "n": 46876,
      "K": 512,
      "effective_num_bins": 512,
      "raw": {
        "train_min": 670.0,
        "train_max": 3363.0,
        "train_range": 2693.0,
        "num_unique": 1774,
        "zero_ratio": 0.0,
        "is_constant": false
      },
      "token": {
        "num_tokens_used": 430,
        "bins_used": 430,
        "possible_unique": 512,
        "preserve_ratio": 0.83984375,
        "unique_preserve_ratio": 0.83984375,
        "compression_factor": 4.125581395348838,
        "entropy_norm": 0.8159414506137578,
        "quantiles": {
          "min": 0,
          "q10": 147,
          "q25": 168,
          "q75": 269,
          "q90": 285,
          "max": 511
        }
      },
      "decision": {
        "label": "transform",
        "reasons": [
          "low_preserve_ratio"
        ],
        "thresholds": {
          "preserve_threshold": 0.95,
          "compression_threshold": 8.0,
          "entropy_threshold": 0.75,
          "entropy_trigger_requires_raw_unique_gt_K": true
        }
      }
    },
    {
      "feature": "dlllist.avg_dlls_per_proc",
      "n": 46876,
      "K": 512,
      "effective_num_bins": 512,
      "raw": {
        "train_min": 7.333333333,
        "train_max": 53.17073171,
        "train_range": 45.837398377,
        "num_unique": 13330,
        "zero_ratio": 0.0,
        "is_constant": false
      },
      "token": {
        "num_tokens_used": 365,
        "bins_used": 365,
        "possible_unique": 512,
        "preserve_ratio": 0.712890625,
        "unique_preserve_ratio": 0.712890625,
        "compression_factor": 36.52054794520548,
        "entropy_norm": 0.7999558733839494,
        "quantiles": {
          "min": 0,
          "q10": 339,
          "q25": 351,
          "q75": 472,
          "q90": 492,
          "max": 511
        }
      },
      "decision": {
        "label": "transform",
        "reasons": [
          "low_preserve_ratio",
          "high_compression_factor"
        ],
        "thresholds": {
          "preserve_threshold": 0.95,
          "compression_threshold": 8.0,
          "entropy_threshold": 0.75,
          "entropy_trigger_requires_raw_unique_gt_K": true
        }
      }
    },
    {
      "feature": "handles.nhandles",
      "n": 46876,
      "K": 512,
      "effective_num_bins": 512,
      "raw": {
        "train_min": 3514.0,
        "train_max": 48156.0,
        "train_range": 44642.0,
        "num_unique": 7189,
        "zero_ratio": 0.0,
        "is_constant": false
      },
      "token": {
        "num_tokens_used": 217,
        "bins_used": 217,
        "possible_unique": 512,
        "preserve_ratio": 0.423828125,
        "unique_preserve_ratio": 0.423828125,
        "compression_factor": 33.12903225806452,
        "entropy_norm": 0.7595982834699794,
        "quantiles": {
          "min": 0,
          "q10": 51,
          "q25": 55,
          "q75": 99,
          "q90": 105,
          "max": 511
        }
      },
      "decision": {
        "label": "transform",
        "reasons": [
          "low_preserve_ratio",
          "high_compression_factor"
        ],
        "thresholds": {
          "preserve_threshold": 0.95,
          "compression_threshold": 8.0,
          "entropy_threshold": 0.75,
          "entropy_trigger_requires_raw_unique_gt_K": true
        }
      }
    },
    {
      "feature": "handles.avg_handles_per_proc",
      "n": 46876,
      "K": 512,
      "effective_num_bins": 512,
      "raw": {
        "train_min": 71.13924051,
        "train_max": 1174.536585,
        "train_range": 1103.39734449,
        "num_unique": 29752,
        "zero_ratio": 0.0,
        "is_constant": false
      },
      "token": {
        "num_tokens_used": 169,
        "bins_used": 169,
        "possible_unique": 512,
        "preserve_ratio": 0.330078125,
        "unique_preserve_ratio": 0.330078125,
        "compression_factor": 176.0473372781065,
        "entropy_norm": 0.7307957686317256,
        "quantiles": {
          "min": 0,
          "q10": 60,
          "q25": 64,
          "q75": 102,
          "q90": 107,
          "max": 511
        }
      },
      "decision": {
        "label": "transform",
        "reasons": [
          "low_preserve_ratio",
          "high_compression_factor",
          "low_entropy_norm_high_unique"
        ],
        "thresholds": {
          "preserve_threshold": 0.95,
          "compression_threshold": 8.0,
          "entropy_threshold": 0.75,
          "entropy_trigger_requires_raw_unique_gt_K": true
        }
      }
    },
    {
      "feature": "handles.nport",
      "n": 46876,
      "K": 512,
      "effective_num_bins": 512,
      "raw": {
        "train_min": 0.0,
        "train_max": 0.0,
        "train_range": 0.0,
        "num_unique": 1,
        "zero_ratio": 1.0,
        "is_constant": true
      },
      "token": {
        "num_tokens_used": 1,
        "bins_used": 1,
        "possible_unique": 1,
        "preserve_ratio": 1.0,
        "unique_preserve_ratio": 1.0,
        "compression_factor": 1.0,
        "entropy_norm": 1.0,
        "quantiles": {
          "min": 0,
          "q10": 0,
          "q25": 0,
          "q75": 0,
          "q90": 0,
          "max": 0
        }
      },
      "decision": {
        "label": "drop",
        "reasons": [
          "constant_feature"
        ],
        "thresholds": {
          "preserve_threshold": 0.95,
          "compression_threshold": 8.0,
          "entropy_threshold": 0.75,
          "entropy_trigger_requires_raw_unique_gt_K": true
        }
      }
    },
    {
      "feature": "handles.nfile",
      "n": 46876,
      "K": 512,
      "effective_num_bins": 512,
      "raw": {
        "train_min": 266.0,
        "train_max": 40605.0,
        "train_range": 40339.0,
        "num_unique": 1093,
        "zero_ratio": 0.0,
        "is_constant": false
      },
      "token": {
        "num_tokens_used": 101,
        "bins_used": 101,
        "possible_unique": 512,
        "preserve_ratio": 0.197265625,
        "unique_preserve_ratio": 0.197265625,
        "compression_factor": 10.821782178217822,
        "entropy_norm": 0.43316236321273,
        "quantiles": {
          "min": 0,
          "q10": 4,
          "q25": 4,
          "q75": 10,
          "q90": 11,
          "max": 511
        }
      },
      "decision": {
        "label": "transform",
        "reasons": [
          "low_preserve_ratio",
          "high_compression_factor",
          "low_entropy_norm_high_unique"
        ],
        "thresholds": {
          "preserve_threshold": 0.95,
          "compression_threshold": 8.0,
          "entropy_threshold": 0.75,
          "entropy_trigger_requires_raw_unique_gt_K": true
        }
      }
    },
    {
      "feature": "handles.nevent",
      "n": 46876,
      "K": 512,
      "effective_num_bins": 512,
      "raw": {
        "train_min": 966.0,
        "train_max": 7892.0,
        "train_range": 6926.0,
        "num_unique": 3322,
        "zero_ratio": 0.0,
        "is_constant": false
      },
      "token": {
        "num_tokens_used": 356,
        "bins_used": 356,
        "possible_unique": 512,
        "preserve_ratio": 0.6953125,
        "unique_preserve_ratio": 0.6953125,
        "compression_factor": 9.331460674157304,
        "entropy_norm": 0.8177864870258066,
        "quantiles": {
          "min": 0,
          "q10": 136,
          "q25": 144,
          "q75": 248,
          "q90": 267,
          "max": 511
        }
      },
      "decision": {
        "label": "transform",
        "reasons": [
          "low_preserve_ratio",
          "high_compression_factor"
        ],
        "thresholds": {
          "preserve_threshold": 0.95,
          "compression_threshold": 8.0,
          "entropy_threshold": 0.75,
          "entropy_trigger_requires_raw_unique_gt_K": true
        }
      }
    },
    {
      "feature": "handles.ndesktop",
      "n": 46876,
      "K": 512,
      "effective_num_bins": 512,
      "raw": {
        "train_min": 22.0,
        "train_max": 159.0,
        "train_range": 137.0,
        "num_unique": 60,
        "zero_ratio": 0.0,
        "is_constant": false
      },
      "token": {
        "num_tokens_used": 60,
        "bins_used": 60,
        "possible_unique": 60,
        "preserve_ratio": 1.0,
        "unique_preserve_ratio": 1.0,
        "compression_factor": 1.0,
        "entropy_norm": 0.6624280875547963,
        "quantiles": {
          "min": 0,
          "q10": 67,
          "q25": 78,
          "q75": 89,
          "q90": 97,
          "max": 511
        }
      },
      "decision": {
        "label": "keep",
        "reasons": [
          "metrics_within_thresholds"
        ],
        "thresholds": {
          "preserve_threshold": 0.95,
          "compression_threshold": 8.0,
          "entropy_threshold": 0.75,
          "entropy_trigger_requires_raw_unique_gt_K": true
        }
      }
    },
    {
      "feature": "handles.nkey",
      "n": 46876,
      "K": 512,
      "effective_num_bins": 512,
      "raw": {
        "train_min": 284.0,
        "train_max": 2668.0,
        "train_range": 2384.0,
        "num_unique": 1060,
        "zero_ratio": 0.0,
        "is_constant": false
      },
      "token": {
        "num_tokens_used": 299,
        "bins_used": 299,
        "possible_unique": 512,
        "preserve_ratio": 0.583984375,
        "unique_preserve_ratio": 0.583984375,
        "compression_factor": 3.5451505016722407,
        "entropy_norm": 0.7672024688849309,
        "quantiles": {
          "min": 0,
          "q10": 80,
          "q25": 83,
          "q75": 123,
          "q90": 139,
          "max": 511
        }
      },
      "decision": {
        "label": "transform",
        "reasons": [
          "low_preserve_ratio"
        ],
        "thresholds": {
          "preserve_threshold": 0.95,
          "compression_threshold": 8.0,
          "entropy_threshold": 0.75,
          "entropy_trigger_requires_raw_unique_gt_K": true
        }
      }
    },
    {
      "feature": "handles.nthread",
      "n": 46876,
      "K": 512,
      "effective_num_bins": 512,
      "raw": {
        "train_min": 388.0,
        "train_max": 2026.0,
        "train_range": 1638.0,
        "num_unique": 1149,
        "zero_ratio": 0.0,
        "is_constant": false
      },
      "token": {
        "num_tokens_used": 400,
        "bins_used": 400,
        "possible_unique": 512,
        "preserve_ratio": 0.78125,
        "unique_preserve_ratio": 0.78125,
        "compression_factor": 2.8725,
        "entropy_norm": 0.8727956649786135,
        "quantiles": {
          "min": 0,
          "q10": 86,
          "q25": 99,
          "q75": 244,
          "q90": 261,
          "max": 511
        }
      },
      "decision": {
        "label": "transform",
        "reasons": [
          "low_preserve_ratio"
        ],
        "thresholds": {
          "preserve_threshold": 0.95,
          "compression_threshold": 8.0,
          "entropy_threshold": 0.75,
          "entropy_trigger_requires_raw_unique_gt_K": true
        }
      }
    },
    {
      "feature": "handles.ndirectory",
      "n": 46876,
      "K": 512,
      "effective_num_bins": 512,
      "raw": {
        "train_min": 57.0,
        "train_max": 310.0,
        "train_range": 253.0,
        "num_unique": 104,
        "zero_ratio": 0.0,
        "is_constant": false
      },
      "token": {
        "num_tokens_used": 104,
        "bins_used": 104,
        "possible_unique": 104,
        "preserve_ratio": 1.0,
        "unique_preserve_ratio": 1.0,
        "compression_factor": 1.0,
        "entropy_norm": 0.7041268139450781,
        "quantiles": {
          "min": 0,
          "q10": 70,
          "q25": 84,
          "q75": 101,
          "q90": 105,
          "max": 511
        }
      },
      "decision": {
        "label": "keep",
        "reasons": [
          "metrics_within_thresholds"
        ],
        "thresholds": {
          "preserve_threshold": 0.95,
          "compression_threshold": 8.0,
          "entropy_threshold": 0.75,
          "entropy_trigger_requires_raw_unique_gt_K": true
        }
      }
    },
    {
      "feature": "handles.nsemaphore",
      "n": 46876,
      "K": 512,
      "effective_num_bins": 512,
      "raw": {
        "train_min": 296.0,
        "train_max": 1029.0,
        "train_range": 733.0,
        "num_unique": 624,
        "zero_ratio": 0.0,
        "is_constant": false
      },
      "token": {
        "num_tokens_used": 442,
        "bins_used": 442,
        "possible_unique": 512,
        "preserve_ratio": 0.86328125,
        "unique_preserve_ratio": 0.86328125,
        "compression_factor": 1.411764705882353,
        "entropy_norm": 0.7973469923194322,
        "quantiles": {
          "min": 0,
          "q10": 209,
          "q25": 221,
          "q75": 317,
          "q90": 335,
          "max": 511
        }
      },
      "decision": {
        "label": "transform",
        "reasons": [
          "low_preserve_ratio"
        ],
        "thresholds": {
          "preserve_threshold": 0.95,
          "compression_threshold": 8.0,
          "entropy_threshold": 0.75,
          "entropy_trigger_requires_raw_unique_gt_K": true
        }
      }
    },
    {
      "feature": "handles.ntimer",
      "n": 46876,
      "K": 512,
      "effective_num_bins": 512,
      "raw": {
        "train_min": 69.0,
        "train_max": 222.0,
        "train_range": 153.0,
        "num_unique": 123,
        "zero_ratio": 0.0,
        "is_constant": false
      },
      "token": {
        "num_tokens_used": 123,
        "bins_used": 123,
        "possible_unique": 123,
        "preserve_ratio": 1.0,
        "unique_preserve_ratio": 1.0,
        "compression_factor": 1.0,
        "entropy_norm": 0.7453838702889035,
        "quantiles": {
          "min": 0,
          "q10": 147,
          "q25": 170,
          "q75": 244,
          "q90": 257,
          "max": 511
        }
      },
      "decision": {
        "label": "keep",
        "reasons": [
          "metrics_within_thresholds"
        ],
        "thresholds": {
          "preserve_threshold": 0.95,
          "compression_threshold": 8.0,
          "entropy_threshold": 0.75,
          "entropy_trigger_requires_raw_unique_gt_K": true
        }
      }
    },
    {
      "feature": "handles.nsection",
      "n": 46876,
      "K": 512,
      "effective_num_bins": 512,
      "raw": {
        "train_min": 50.0,
        "train_max": 14687.0,
        "train_range": 14637.0,
        "num_unique": 612,
        "zero_ratio": 0.0,
        "is_constant": false
      },
      "token": {
        "num_tokens_used": 36,
        "bins_used": 36,
        "possible_unique": 512,
        "preserve_ratio": 0.0703125,
        "unique_preserve_ratio": 0.0703125,
        "compression_factor": 17.0,
        "entropy_norm": 0.6262752278495087,
        "quantiles": {
          "min": 0,
          "q10": 3,
          "q25": 4,
          "q75": 12,
          "q90": 13,
          "max": 511
        }
      },
      "decision": {
        "label": "transform",
        "reasons": [
          "low_preserve_ratio",
          "high_compression_factor",
          "low_entropy_norm_high_unique"
        ],
        "thresholds": {
          "preserve_threshold": 0.95,
          "compression_threshold": 8.0,
          "entropy_threshold": 0.75,
          "entropy_trigger_requires_raw_unique_gt_K": true
        }
      }
    },
    {
      "feature": "handles.nmutant",
      "n": 46876,
      "K": 512,
      "effective_num_bins": 512,
      "raw": {
        "train_min": 118.0,
        "train_max": 583.0,
        "train_range": 465.0,
        "num_unique": 405,
        "zero_ratio": 0.0,
        "is_constant": false
      },
      "token": {
        "num_tokens_used": 405,
        "bins_used": 405,
        "possible_unique": 405,
        "preserve_ratio": 1.0,
        "unique_preserve_ratio": 1.0,
        "compression_factor": 1.0,
        "entropy_norm": 0.8406808847747658,
        "quantiles": {
          "min": 0,
          "q10": 123,
          "q25": 154,
          "q75": 273,
          "q90": 318,
          "max": 511
        }
      },
      "decision": {
        "label": "keep",
        "reasons": [
          "metrics_within_thresholds"
        ],
        "thresholds": {
          "preserve_threshold": 0.95,
          "compression_threshold": 8.0,
          "entropy_threshold": 0.75,
          "entropy_trigger_requires_raw_unique_gt_K": true
        }
      }
    },
    {
      "feature": "ldrmodules.not_in_load",
      "n": 46876,
      "K": 512,
      "effective_num_bins": 512,
      "raw": {
        "train_min": 6.0,
        "train_max": 238.0,
        "train_range": 232.0,
        "num_unique": 145,
        "zero_ratio": 0.0,
        "is_constant": false
      },
      "token": {
        "num_tokens_used": 145,
        "bins_used": 145,
        "possible_unique": 145,
        "preserve_ratio": 1.0,
        "unique_preserve_ratio": 1.0,
        "compression_factor": 1.0,
        "entropy_norm": 0.7895089801293358,
        "quantiles": {
          "min": 0,
          "q10": 81,
          "q25": 88,
          "q75": 150,
          "q90": 176,
          "max": 511
        }
      },
      "decision": {
        "label": "keep",
        "reasons": [
          "metrics_within_thresholds"
        ],
        "thresholds": {
          "preserve_threshold": 0.95,
          "compression_threshold": 8.0,
          "entropy_threshold": 0.75,
          "entropy_trigger_requires_raw_unique_gt_K": true
        }
      }
    },
    {
      "feature": "ldrmodules.not_in_init",
      "n": 46876,
      "K": 512,
      "effective_num_bins": 512,
      "raw": {
        "train_min": 16.0,
        "train_max": 262.0,
        "train_range": 246.0,
        "num_unique": 180,
        "zero_ratio": 0.0,
        "is_constant": false
      },
      "token": {
        "num_tokens_used": 180,
        "bins_used": 180,
        "possible_unique": 180,
        "preserve_ratio": 1.0,
        "unique_preserve_ratio": 1.0,
        "compression_factor": 1.0,
        "entropy_norm": 0.8092464216910374,
        "quantiles": {
          "min": 0,
          "q10": 131,
          "q25": 143,
          "q75": 206,
          "q90": 228,
          "max": 511
        }
      },
      "decision": {
        "label": "keep",
        "reasons": [
          "metrics_within_thresholds"
        ],
        "thresholds": {
          "preserve_threshold": 0.95,
          "compression_threshold": 8.0,
          "entropy_threshold": 0.75,
          "entropy_trigger_requires_raw_unique_gt_K": true
        }
      }
    },
    {
      "feature": "ldrmodules.not_in_mem",
      "n": 46876,
      "K": 512,
      "effective_num_bins": 512,
      "raw": {
        "train_min": 6.0,
        "train_max": 238.0,
        "train_range": 232.0,
        "num_unique": 145,
        "zero_ratio": 0.0,
        "is_constant": false
      },
      "token": {
        "num_tokens_used": 145,
        "bins_used": 145,
        "possible_unique": 145,
        "preserve_ratio": 1.0,
        "unique_preserve_ratio": 1.0,
        "compression_factor": 1.0,
        "entropy_norm": 0.7895867867854146,
        "quantiles": {
          "min": 0,
          "q10": 81,
          "q25": 88,
          "q75": 150,
          "q90": 176,
          "max": 511
        }
      },
      "decision": {
        "label": "keep",
        "reasons": [
          "metrics_within_thresholds"
        ],
        "thresholds": {
          "preserve_threshold": 0.95,
          "compression_threshold": 8.0,
          "entropy_threshold": 0.75,
          "entropy_trigger_requires_raw_unique_gt_K": true
        }
      }
    },
    {
      "feature": "ldrmodules.not_in_load_avg",
      "n": 46876,
      "K": 512,
      "effective_num_bins": 512,
      "raw": {
        "train_min": 0.016176471,
        "train_max": 0.531120332,
        "train_range": 0.514943861,
        "num_unique": 15444,
        "zero_ratio": 0.0,
        "is_constant": false
      },
      "token": {
        "num_tokens_used": 119,
        "bins_used": 119,
        "possible_unique": 512,
        "preserve_ratio": 0.232421875,
        "unique_preserve_ratio": 0.232421875,
        "compression_factor": 129.78151260504202,
        "entropy_norm": 0.5983356558920351,
        "quantiles": {
          "min": 0,
          "q10": 11,
          "q25": 12,
          "q75": 20,
          "q90": 24,
          "max": 511
        }
      },
      "decision": {
        "label": "transform",
        "reasons": [
          "low_preserve_ratio",
          "high_compression_factor",
          "low_entropy_norm_high_unique"
        ],
        "thresholds": {
          "preserve_threshold": 0.95,
          "compression_threshold": 8.0,
          "entropy_threshold": 0.75,
          "entropy_trigger_requires_raw_unique_gt_K": true
        }
      }
    },
    {
      "feature": "ldrmodules.not_in_init_avg",
      "n": 46876,
      "K": 512,
      "effective_num_bins": 512,
      "raw": {
        "train_min": 0.040525739,
        "train_max": 0.585062241,
        "train_range": 0.544536502,
        "num_unique": 15577,
        "zero_ratio": 0.0,
        "is_constant": false
      },
      "token": {
        "num_tokens_used": 140,
        "bins_used": 140,
        "possible_unique": 512,
        "preserve_ratio": 0.2734375,
        "unique_preserve_ratio": 0.2734375,
        "compression_factor": 111.26428571428572,
        "entropy_norm": 0.5284157849722646,
        "quantiles": {
          "min": 0,
          "q10": 10,
          "q25": 11,
          "q75": 14,
          "q90": 19,
          "max": 511
        }
      },
      "decision": {
        "label": "transform",
        "reasons": [
          "low_preserve_ratio",
          "high_compression_factor",
          "low_entropy_norm_high_unique"
        ],
        "thresholds": {
          "preserve_threshold": 0.95,
          "compression_threshold": 8.0,
          "entropy_threshold": 0.75,
          "entropy_trigger_requires_raw_unique_gt_K": true
        }
      }
    },
    {
      "feature": "ldrmodules.not_in_mem_avg",
      "n": 46876,
      "K": 512,
      "effective_num_bins": 512,
      "raw": {
        "train_min": 0.016176471,
        "train_max": 0.531120332,
        "train_range": 0.514943861,
        "num_unique": 15444,
        "zero_ratio": 0.0,
        "is_constant": false
      },
      "token": {
        "num_tokens_used": 120,
        "bins_used": 120,
        "possible_unique": 512,
        "preserve_ratio": 0.234375,
        "unique_preserve_ratio": 0.234375,
        "compression_factor": 128.7,
        "entropy_norm": 0.5971983310391107,
        "quantiles": {
          "min": 0,
          "q10": 11,
          "q25": 12,
          "q75": 20,
          "q90": 24,
          "max": 511
        }
      },
      "decision": {
        "label": "transform",
        "reasons": [
          "low_preserve_ratio",
          "high_compression_factor",
          "low_entropy_norm_high_unique"
        ],
        "thresholds": {
          "preserve_threshold": 0.95,
          "compression_threshold": 8.0,
          "entropy_threshold": 0.75,
          "entropy_trigger_requires_raw_unique_gt_K": true
        }
      }
    },
    {
      "feature": "malfind.ninjections",
      "n": 46876,
      "K": 512,
      "effective_num_bins": 512,
      "raw": {
        "train_min": 1.0,
        "train_max": 627.0,
        "train_range": 626.0,
        "num_unique": 111,
        "zero_ratio": 0.0,
        "is_constant": false
      },
      "token": {
        "num_tokens_used": 94,
        "bins_used": 94,
        "possible_unique": 111,
        "preserve_ratio": 0.8468468468468469,
        "unique_preserve_ratio": 0.8468468468468469,
        "compression_factor": 1.1808510638297873,
        "entropy_norm": 0.4052976416649532,
        "quantiles": {
          "min": 0,
          "q10": 1,
          "q25": 1,
          "q75": 3,
          "q90": 5,
          "max": 511
        }
      },
      "decision": {
        "label": "transform",
        "reasons": [
          "low_preserve_ratio"
        ],
        "thresholds": {
          "preserve_threshold": 0.95,
          "compression_threshold": 8.0,
          "entropy_threshold": 0.75,
          "entropy_trigger_requires_raw_unique_gt_K": true
        }
      }
    },
    {
      "feature": "malfind.commitCharge",
      "n": 46876,
      "K": 512,
      "effective_num_bins": 512,
      "raw": {
        "train_min": 1.0,
        "train_max": 220850.0,
        "train_range": 220849.0,
        "num_unique": 488,
        "zero_ratio": 0.0,
        "is_constant": false
      },
      "token": {
        "num_tokens_used": 94,
        "bins_used": 94,
        "possible_unique": 488,
        "preserve_ratio": 0.19262295081967212,
        "unique_preserve_ratio": 0.19262295081967212,
        "compression_factor": 5.191489361702128,
        "entropy_norm": 0.063477778895545,
        "quantiles": {
          "min": 0,
          "q10": 0,
          "q25": 0,
          "q75": 0,
          "q90": 0,
          "max": 511
        }
      },
      "decision": {
        "label": "transform",
        "reasons": [
          "low_preserve_ratio"
        ],
        "thresholds": {
          "preserve_threshold": 0.95,
          "compression_threshold": 8.0,
          "entropy_threshold": 0.75,
          "entropy_trigger_requires_raw_unique_gt_K": true
        }
      }
    },
    {
      "feature": "malfind.protection",
      "n": 46876,
      "K": 512,
      "effective_num_bins": 512,
      "raw": {
        "train_min": 6.0,
        "train_max": 3762.0,
        "train_range": 3756.0,
        "num_unique": 203,
        "zero_ratio": 0.0,
        "is_constant": false
      },
      "token": {
        "num_tokens_used": 94,
        "bins_used": 94,
        "possible_unique": 203,
        "preserve_ratio": 0.4630541871921182,
        "unique_preserve_ratio": 0.4630541871921182,
        "compression_factor": 2.1595744680851063,
        "entropy_norm": 0.409675969217506,
        "quantiles": {
          "min": 0,
          "q10": 1,
          "q25": 1,
          "q75": 3,
          "q90": 5,
          "max": 511
        }
      },
      "decision": {
        "label": "transform",
        "reasons": [
          "low_preserve_ratio"
        ],
        "thresholds": {
          "preserve_threshold": 0.95,
          "compression_threshold": 8.0,
          "entropy_threshold": 0.75,
          "entropy_trigger_requires_raw_unique_gt_K": true
        }
      }
    },
    {
      "feature": "malfind.uniqueInjections",
      "n": 46876,
      "K": 512,
      "effective_num_bins": 512,
      "raw": {
        "train_min": 1.0,
        "train_max": 90.66666667,
        "train_range": 89.66666667,
        "num_unique": 4452,
        "zero_ratio": 0.0,
        "is_constant": false
      },
      "token": {
        "num_tokens_used": 107,
        "bins_used": 107,
        "possible_unique": 512,
        "preserve_ratio": 0.208984375,
        "unique_preserve_ratio": 0.208984375,
        "compression_factor": 41.60747663551402,
        "entropy_norm": 0.32778636521643384,
        "quantiles": {
          "min": 0,
          "q10": 0,
          "q25": 0,
          "q75": 1,
          "q90": 3,
          "max": 511
        }
      },
      "decision": {
        "label": "transform",
        "reasons": [
          "low_preserve_ratio",
          "high_compression_factor",
          "low_entropy_norm_high_unique"
        ],
        "thresholds": {
          "preserve_threshold": 0.95,
          "compression_threshold": 8.0,
          "entropy_threshold": 0.75,
          "entropy_trigger_requires_raw_unique_gt_K": true
        }
      }
    },
    {
      "feature": "psxview.not_in_pslist",
      "n": 46876,
      "K": 512,
      "effective_num_bins": 512,
      "raw": {
        "train_min": 0.0,
        "train_max": 43.0,
        "train_range": 43.0,
        "num_unique": 40,
        "zero_ratio": 0.4979307108115027,
        "is_constant": false
      },
      "token": {
        "num_tokens_used": 40,
        "bins_used": 40,
        "possible_unique": 40,
        "preserve_ratio": 1.0,
        "unique_preserve_ratio": 1.0,
        "compression_factor": 1.0,
        "entropy_norm": 0.48112950986746617,
        "quantiles": {
          "min": 0,
          "q10": 0,
          "q25": 0,
          "q75": 35,
          "q90": 59,
          "max": 511
        }
      },
      "decision": {
        "label": "keep",
        "reasons": [
          "metrics_within_thresholds"
        ],
        "thresholds": {
          "preserve_threshold": 0.95,
          "compression_threshold": 8.0,
          "entropy_threshold": 0.75,
          "entropy_trigger_requires_raw_unique_gt_K": true
        }
      }
    },
    {
      "feature": "psxview.not_in_eprocess_pool",
      "n": 46876,
      "K": 512,
      "effective_num_bins": 512,
      "raw": {
        "train_min": 0.0,
        "train_max": 1.0,
        "train_range": 1.0,
        "num_unique": 2,
        "zero_ratio": 0.9978027135421111,
        "is_constant": false
      },
      "token": {
        "num_tokens_used": 2,
        "bins_used": 2,
        "possible_unique": 2,
        "preserve_ratio": 1.0,
        "unique_preserve_ratio": 1.0,
        "compression_factor": 1.0,
        "entropy_norm": 0.022568703168667884,
        "quantiles": {
          "min": 0,
          "q10": 0,
          "q25": 0,
          "q75": 0,
          "q90": 0,
          "max": 511
        }
      },
      "decision": {
        "label": "keep",
        "reasons": [
          "metrics_within_thresholds"
        ],
        "thresholds": {
          "preserve_threshold": 0.95,
          "compression_threshold": 8.0,
          "entropy_threshold": 0.75,
          "entropy_trigger_requires_raw_unique_gt_K": true
        }
      }
    },
    {
      "feature": "psxview.not_in_ethread_pool",
      "n": 46876,
      "K": 512,
      "effective_num_bins": 512,
      "raw": {
        "train_min": 0.0,
        "train_max": 201.0,
        "train_range": 201.0,
        "num_unique": 78,
        "zero_ratio": 0.43839064766618313,
        "is_constant": false
      },
      "token": {
        "num_tokens_used": 78,
        "bins_used": 78,
        "possible_unique": 78,
        "preserve_ratio": 1.0,
        "unique_preserve_ratio": 1.0,
        "compression_factor": 1.0,
        "entropy_norm": 0.4418943899437724,
        "quantiles": {
          "min": 0,
          "q10": 0,
          "q25": 0,
          "q75": 7,
          "q90": 15,
          "max": 511
        }
      },
      "decision": {
        "label": "keep",
        "reasons": [
          "metrics_within_thresholds"
        ],
        "thresholds": {
          "preserve_threshold": 0.95,
          "compression_threshold": 8.0,
          "entropy_threshold": 0.75,
          "entropy_trigger_requires_raw_unique_gt_K": true
        }
      }
    },
    {
      "feature": "psxview.not_in_pspcid_list",
      "n": 46876,
      "K": 512,
      "effective_num_bins": 512,
      "raw": {
        "train_min": 0.0,
        "train_max": 43.0,
        "train_range": 43.0,
        "num_unique": 40,
        "zero_ratio": 0.4978667121768069,
        "is_constant": false
      },
      "token": {
        "num_tokens_used": 40,
        "bins_used": 40,
        "possible_unique": 40,
        "preserve_ratio": 1.0,
        "unique_preserve_ratio": 1.0,
        "compression_factor": 1.0,
        "entropy_norm": 0.48127220495434797,
        "quantiles": {
          "min": 0,
          "q10": 0,
          "q25": 0,
          "q75": 35,
          "q90": 59,
          "max": 511
        }
      },
      "decision": {
        "label": "keep",
        "reasons": [
          "metrics_within_thresholds"
        ],
        "thresholds": {
          "preserve_threshold": 0.95,
          "compression_threshold": 8.0,
          "entropy_threshold": 0.75,
          "entropy_trigger_requires_raw_unique_gt_K": true
        }
      }
    },
    {
      "feature": "psxview.not_in_csrss_handles",
      "n": 46876,
      "K": 512,
      "effective_num_bins": 512,
      "raw": {
        "train_min": 4.0,
        "train_max": 205.0,
        "train_range": 201.0,
        "num_unique": 78,
        "zero_ratio": 0.0,
        "is_constant": false
      },
      "token": {
        "num_tokens_used": 78,
        "bins_used": 78,
        "possible_unique": 78,
        "preserve_ratio": 1.0,
        "unique_preserve_ratio": 1.0,
        "compression_factor": 1.0,
        "entropy_norm": 0.4422737565982476,
        "quantiles": {
          "min": 0,
          "q10": 0,
          "q25": 0,
          "q75": 7,
          "q90": 15,
          "max": 511
        }
      },
      "decision": {
        "label": "keep",
        "reasons": [
          "metrics_within_thresholds"
        ],
        "thresholds": {
          "preserve_threshold": 0.95,
          "compression_threshold": 8.0,
          "entropy_threshold": 0.75,
          "entropy_trigger_requires_raw_unique_gt_K": true
        }
      }
    },
    {
      "feature": "psxview.not_in_session",
      "n": 46876,
      "K": 512,
      "effective_num_bins": 512,
      "raw": {
        "train_min": 2.0,
        "train_max": 45.0,
        "train_range": 43.0,
        "num_unique": 40,
        "zero_ratio": 0.0,
        "is_constant": false
      },
      "token": {
        "num_tokens_used": 40,
        "bins_used": 40,
        "possible_unique": 40,
        "preserve_ratio": 1.0,
        "unique_preserve_ratio": 1.0,
        "compression_factor": 1.0,
        "entropy_norm": 0.48106061802204303,
        "quantiles": {
          "min": 0,
          "q10": 0,
          "q25": 0,
          "q75": 35,
          "q90": 59,
          "max": 511
        }
      },
      "decision": {
        "label": "keep",
        "reasons": [
          "metrics_within_thresholds"
        ],
        "thresholds": {
          "preserve_threshold": 0.95,
          "compression_threshold": 8.0,
          "entropy_threshold": 0.75,
          "entropy_trigger_requires_raw_unique_gt_K": true
        }
      }
    },
    {
      "feature": "psxview.not_in_deskthrd",
      "n": 46876,
      "K": 512,
      "effective_num_bins": 512,
      "raw": {
        "train_min": 4.0,
        "train_max": 207.0,
        "train_range": 203.0,
        "num_unique": 82,
        "zero_ratio": 0.0,
        "is_constant": false
      },
      "token": {
        "num_tokens_used": 82,
        "bins_used": 82,
        "possible_unique": 82,
        "preserve_ratio": 1.0,
        "unique_preserve_ratio": 1.0,
        "compression_factor": 1.0,
        "entropy_norm": 0.4825476873484649,
        "quantiles": {
          "min": 0,
          "q10": 5,
          "q25": 5,
          "q75": 12,
          "q90": 20,
          "max": 511
        }
      },
      "decision": {
        "label": "keep",
        "reasons": [
          "metrics_within_thresholds"
        ],
        "thresholds": {
          "preserve_threshold": 0.95,
          "compression_threshold": 8.0,
          "entropy_threshold": 0.75,
          "entropy_trigger_requires_raw_unique_gt_K": true
        }
      }
    },
    {
      "feature": "psxview.not_in_pslist_false_avg",
      "n": 46876,
      "K": 512,
      "effective_num_bins": 512,
      "raw": {
        "train_min": 0.0,
        "train_max": 0.551282051,
        "train_range": 0.551282051,
        "num_unique": 7781,
        "zero_ratio": 0.44549449611741615,
        "is_constant": false
      },
      "token": {
        "num_tokens_used": 327,
        "bins_used": 327,
        "possible_unique": 512,
        "preserve_ratio": 0.638671875,
        "unique_preserve_ratio": 0.638671875,
        "compression_factor": 23.795107033639145,
        "entropy_norm": 0.5548446570820458,
        "quantiles": {
          "min": 0,
          "q10": 0,
          "q25": 0,
          "q75": 63,
          "q90": 110,
          "max": 511
        }
      },
      "decision": {
        "label": "transform",
        "reasons": [
          "low_preserve_ratio",
          "high_compression_factor",
          "low_entropy_norm_high_unique"
        ],
        "thresholds": {
          "preserve_threshold": 0.95,
          "compression_threshold": 8.0,
          "entropy_threshold": 0.75,
          "entropy_trigger_requires_raw_unique_gt_K": true
        }
      }
    },
    {
      "feature": "psxview.not_in_eprocess_pool_false_avg",
      "n": 46876,
      "K": 512,
      "effective_num_bins": 512,
      "raw": {
        "train_min": 0.0,
        "train_max": 0.043478261,
        "train_range": 0.043478261,
        "num_unique": 159,
        "zero_ratio": 0.9949227749808004,
        "is_constant": false
      },
      "token": {
        "num_tokens_used": 125,
        "bins_used": 125,
        "possible_unique": 159,
        "preserve_ratio": 0.7861635220125787,
        "unique_preserve_ratio": 0.7861635220125787,
        "compression_factor": 1.272,
        "entropy_norm": 0.011268317127381706,
        "quantiles": {
          "min": 0,
          "q10": 0,
          "q25": 0,
          "q75": 0,
          "q90": 0,
          "max": 511
        }
      },
      "decision": {
        "label": "transform",
        "reasons": [
          "low_preserve_ratio"
        ],
        "thresholds": {
          "preserve_threshold": 0.95,
          "compression_threshold": 8.0,
          "entropy_threshold": 0.75,
          "entropy_trigger_requires_raw_unique_gt_K": true
        }
      }
    },
    {
      "feature": "psxview.not_in_ethread_pool_false_avg",
      "n": 46876,
      "K": 512,
      "effective_num_bins": 512,
      "raw": {
        "train_min": 0.0,
        "train_max": 0.8375,
        "train_range": 0.8375,
        "num_unique": 8346,
        "zero_ratio": 0.38751173308302755,
        "is_constant": false
      },
      "token": {
        "num_tokens_used": 320,
        "bins_used": 320,
        "possible_unique": 512,
        "preserve_ratio": 0.625,
        "unique_preserve_ratio": 0.625,
        "compression_factor": 26.08125,
        "entropy_norm": 0.567835293379793,
        "quantiles": {
          "min": 0,
          "q10": 0,
          "q25": 0,
          "q75": 42,
          "q90": 81,
          "max": 511
        }
      },
      "decision": {
        "label": "transform",
        "reasons": [
          "low_preserve_ratio",
          "high_compression_factor",
          "low_entropy_norm_high_unique"
        ],
        "thresholds": {
          "preserve_threshold": 0.95,
          "compression_threshold": 8.0,
          "entropy_threshold": 0.75,
          "entropy_trigger_requires_raw_unique_gt_K": true
        }
      }
    },
    {
      "feature": "psxview.not_in_pspcid_list_false_avg",
      "n": 46876,
      "K": 512,
      "effective_num_bins": 512,
      "raw": {
        "train_min": 0.0,
        "train_max": 1.0,
        "train_range": 1.0,
        "num_unique": 7783,
        "zero_ratio": 0.44543049748272034,
        "is_constant": false
      },
      "token": {
        "num_tokens_used": 210,
        "bins_used": 210,
        "possible_unique": 512,
        "preserve_ratio": 0.41015625,
        "unique_preserve_ratio": 0.41015625,
        "compression_factor": 37.06190476190476,
        "entropy_norm": 0.550616529106666,
        "quantiles": {
          "min": 0,
          "q10": 0,
          "q25": 0,
          "q75": 34,
          "q90": 60,
          "max": 511
        }
      },
      "decision": {
        "label": "transform",
        "reasons": [
          "low_preserve_ratio",
          "high_compression_factor",
          "low_entropy_norm_high_unique"
        ],
        "thresholds": {
          "preserve_threshold": 0.95,
          "compression_threshold": 8.0,
          "entropy_threshold": 0.75,
          "entropy_trigger_requires_raw_unique_gt_K": true
        }
      }
    },
    {
      "feature": "psxview.not_in_csrss_handles_false_avg",
      "n": 46876,
      "K": 512,
      "effective_num_bins": 512,
      "raw": {
        "train_min": 0.025806452,
        "train_max": 0.854166667,
        "train_range": 0.828360215,
        "num_unique": 9458,
        "zero_ratio": 0.0,
        "is_constant": false
      },
      "token": {
        "num_tokens_used": 322,
        "bins_used": 322,
        "possible_unique": 512,
        "preserve_ratio": 0.62890625,
        "unique_preserve_ratio": 0.62890625,
        "compression_factor": 29.372670807453417,
        "entropy_norm": 0.73113503495035,
        "quantiles": {
          "min": 0,
          "q10": 41,
          "q25": 45,
          "q75": 86,
          "q90": 121,
          "max": 511
        }
      },
      "decision": {
        "label": "transform",
        "reasons": [
          "low_preserve_ratio",
          "high_compression_factor",
          "low_entropy_norm_high_unique"
        ],
        "thresholds": {
          "preserve_threshold": 0.95,
          "compression_threshold": 8.0,
          "entropy_threshold": 0.75,
          "entropy_trigger_requires_raw_unique_gt_K": true
        }
      }
    },
    {
      "feature": "psxview.not_in_session_false_avg",
      "n": 46876,
      "K": 512,
      "effective_num_bins": 512,
      "raw": {
        "train_min": 0.008333333,
        "train_max": 0.576923077,
        "train_range": 0.568589744,
        "num_unique": 9559,
        "zero_ratio": 0.0,
        "is_constant": false
      },
      "token": {
        "num_tokens_used": 350,
        "bins_used": 350,
        "possible_unique": 512,
        "preserve_ratio": 0.68359375,
        "unique_preserve_ratio": 0.68359375,
        "compression_factor": 27.31142857142857,
        "entropy_norm": 0.731051965549321,
        "quantiles": {
          "min": 0,
          "q10": 33,
          "q25": 36,
          "q75": 94,
          "q90": 139,
          "max": 511
        }
      },
      "decision": {
        "label": "transform",
        "reasons": [
          "low_preserve_ratio",
          "high_compression_factor",
          "low_entropy_norm_high_unique"
        ],
        "thresholds": {
          "preserve_threshold": 0.95,
          "compression_threshold": 8.0,
          "entropy_threshold": 0.75,
          "entropy_trigger_requires_raw_unique_gt_K": true
        }
      }
    },
    {
      "feature": "psxview.not_in_deskthrd_false_avg",
      "n": 46876,
      "K": 512,
      "effective_num_bins": 512,
      "raw": {
        "train_min": 0.04375,
        "train_max": 0.8625,
        "train_range": 0.8187500000000001,
        "num_unique": 9655,
        "zero_ratio": 0.0,
        "is_constant": false
      },
      "token": {
        "num_tokens_used": 332,
        "bins_used": 332,
        "possible_unique": 512,
        "preserve_ratio": 0.6484375,
        "unique_preserve_ratio": 0.6484375,
        "compression_factor": 29.08132530120482,
        "entropy_norm": 0.7308590092265012,
        "quantiles": {
          "min": 0,
          "q10": 57,
          "q25": 64,
          "q75": 104,
          "q90": 139,
          "max": 511
        }
      },
      "decision": {
        "label": "transform",
        "reasons": [
          "low_preserve_ratio",
          "high_compression_factor",
          "low_entropy_norm_high_unique"
        ],
        "thresholds": {
          "preserve_threshold": 0.95,
          "compression_threshold": 8.0,
          "entropy_threshold": 0.75,
          "entropy_trigger_requires_raw_unique_gt_K": true
        }
      }
    },
    {
      "feature": "modules.nmodules",
      "n": 46876,
      "K": 512,
      "effective_num_bins": 512,
      "raw": {
        "train_min": 126.0,
        "train_max": 138.0,
        "train_range": 12.0,
        "num_unique": 3,
        "zero_ratio": 0.0,
        "is_constant": false
      },
      "token": {
        "num_tokens_used": 3,
        "bins_used": 3,
        "possible_unique": 3,
        "preserve_ratio": 1.0,
        "unique_preserve_ratio": 1.0,
        "compression_factor": 1.0,
        "entropy_norm": 0.14893518717453902,
        "quantiles": {
          "min": 0,
          "q10": 511,
          "q25": 511,
          "q75": 511,
          "q90": 511,
          "max": 511
        }
      },
      "decision": {
        "label": "keep",
        "reasons": [
          "metrics_within_thresholds"
        ],
        "thresholds": {
          "preserve_threshold": 0.95,
          "compression_threshold": 8.0,
          "entropy_threshold": 0.75,
          "entropy_trigger_requires_raw_unique_gt_K": true
        }
      }
    },
    {
      "feature": "svcscan.nservices",
      "n": 46876,
      "K": 512,
      "effective_num_bins": 512,
      "raw": {
        "train_min": 94.0,
        "train_max": 395.0,
        "train_range": 301.0,
        "num_unique": 30,
        "zero_ratio": 0.0,
        "is_constant": false
      },
      "token": {
        "num_tokens_used": 30,
        "bins_used": 30,
        "possible_unique": 30,
        "preserve_ratio": 1.0,
        "unique_preserve_ratio": 1.0,
        "compression_factor": 1.0,
        "entropy_norm": 0.34744347879771803,
        "quantiles": {
          "min": 0,
          "q10": 501,
          "q25": 501,
          "q75": 511,
          "q90": 511,
          "max": 511
        }
      },
      "decision": {
        "label": "keep",
        "reasons": [
          "metrics_within_thresholds"
        ],
        "thresholds": {
          "preserve_threshold": 0.95,
          "compression_threshold": 8.0,
          "entropy_threshold": 0.75,
          "entropy_trigger_requires_raw_unique_gt_K": true
        }
      }
    },
    {
      "feature": "svcscan.kernel_drivers",
      "n": 46876,
      "K": 512,
      "effective_num_bins": 512,
      "raw": {
        "train_min": 55.0,
        "train_max": 222.0,
        "train_range": 167.0,
        "num_unique": 19,
        "zero_ratio": 0.0,
        "is_constant": false
      },
      "token": {
        "num_tokens_used": 19,
        "bins_used": 19,
        "possible_unique": 19,
        "preserve_ratio": 1.0,
        "unique_preserve_ratio": 1.0,
        "compression_factor": 1.0,
        "entropy_norm": 0.28582173063131466,
        "quantiles": {
          "min": 0,
          "q10": 508,
          "q25": 508,
          "q75": 511,
          "q90": 511,
          "max": 511
        }
      },
      "decision": {
        "label": "keep",
        "reasons": [
          "metrics_within_thresholds"
        ],
        "thresholds": {
          "preserve_threshold": 0.95,
          "compression_threshold": 8.0,
          "entropy_threshold": 0.75,
          "entropy_trigger_requires_raw_unique_gt_K": true
        }
      }
    },
    {
      "feature": "svcscan.fs_drivers",
      "n": 46876,
      "K": 512,
      "effective_num_bins": 512,
      "raw": {
        "train_min": 6.0,
        "train_max": 26.0,
        "train_range": 20.0,
        "num_unique": 10,
        "zero_ratio": 0.0,
        "is_constant": false
      },
      "token": {
        "num_tokens_used": 10,
        "bins_used": 10,
        "possible_unique": 10,
        "preserve_ratio": 1.0,
        "unique_preserve_ratio": 1.0,
        "compression_factor": 1.0,
        "entropy_norm": 0.0038660702174345973,
        "quantiles": {
          "min": 0,
          "q10": 511,
          "q25": 511,
          "q75": 511,
          "q90": 511,
          "max": 511
        }
      },
      "decision": {
        "label": "keep",
        "reasons": [
          "metrics_within_thresholds"
        ],
        "thresholds": {
          "preserve_threshold": 0.95,
          "compression_threshold": 8.0,
          "entropy_threshold": 0.75,
          "entropy_trigger_requires_raw_unique_gt_K": true
        }
      }
    },
    {
      "feature": "svcscan.process_services",
      "n": 46876,
      "K": 512,
      "effective_num_bins": 512,
      "raw": {
        "train_min": 7.0,
        "train_max": 27.0,
        "train_range": 20.0,
        "num_unique": 14,
        "zero_ratio": 0.0,
        "is_constant": false
      },
      "token": {
        "num_tokens_used": 14,
        "bins_used": 14,
        "possible_unique": 14,
        "preserve_ratio": 1.0,
        "unique_preserve_ratio": 1.0,
        "compression_factor": 1.0,
        "entropy_norm": 0.32624826091756054,
        "quantiles": {
          "min": 0,
          "q10": 435,
          "q25": 435,
          "q75": 511,
          "q90": 511,
          "max": 511
        }
      },
      "decision": {
        "label": "keep",
        "reasons": [
          "metrics_within_thresholds"
        ],
        "thresholds": {
          "preserve_threshold": 0.95,
          "compression_threshold": 8.0,
          "entropy_threshold": 0.75,
          "entropy_trigger_requires_raw_unique_gt_K": true
        }
      }
    },
    {
      "feature": "svcscan.shared_process_services",
      "n": 46876,
      "K": 512,
      "effective_num_bins": 512,
      "raw": {
        "train_min": 26.0,
        "train_max": 118.0,
        "train_range": 92.0,
        "num_unique": 22,
        "zero_ratio": 0.0,
        "is_constant": false
      },
      "token": {
        "num_tokens_used": 22,
        "bins_used": 22,
        "possible_unique": 22,
        "preserve_ratio": 1.0,
        "unique_preserve_ratio": 1.0,
        "compression_factor": 1.0,
        "entropy_norm": 0.276266672668019,
        "quantiles": {
          "min": 0,
          "q10": 500,
          "q25": 500,
          "q75": 511,
          "q90": 511,
          "max": 511
        }
      },
      "decision": {
        "label": "keep",
        "reasons": [
          "metrics_within_thresholds"
        ],
        "thresholds": {
          "preserve_threshold": 0.95,
          "compression_threshold": 8.0,
          "entropy_threshold": 0.75,
          "entropy_trigger_requires_raw_unique_gt_K": true
        }
      }
    },
    {
      "feature": "svcscan.interactive_process_services",
      "n": 46876,
      "K": 512,
      "effective_num_bins": 512,
      "raw": {
        "train_min": 0.0,
        "train_max": 0.0,
        "train_range": 0.0,
        "num_unique": 1,
        "zero_ratio": 1.0,
        "is_constant": true
      },
      "token": {
        "num_tokens_used": 1,
        "bins_used": 1,
        "possible_unique": 1,
        "preserve_ratio": 1.0,
        "unique_preserve_ratio": 1.0,
        "compression_factor": 1.0,
        "entropy_norm": 1.0,
        "quantiles": {
          "min": 0,
          "q10": 0,
          "q25": 0,
          "q75": 0,
          "q90": 0,
          "max": 0
        }
      },
      "decision": {
        "label": "drop",
        "reasons": [
          "constant_feature"
        ],
        "thresholds": {
          "preserve_threshold": 0.95,
          "compression_threshold": 8.0,
          "entropy_threshold": 0.75,
          "entropy_trigger_requires_raw_unique_gt_K": true
        }
      }
    },
    {
      "feature": "svcscan.nactive",
      "n": 46876,
      "K": 512,
      "effective_num_bins": 512,
      "raw": {
        "train_min": 30.0,
        "train_max": 129.0,
        "train_range": 99.0,
        "num_unique": 34,
        "zero_ratio": 0.0,
        "is_constant": false
      },
      "token": {
        "num_tokens_used": 34,
        "bins_used": 34,
        "possible_unique": 34,
        "preserve_ratio": 1.0,
        "unique_preserve_ratio": 1.0,
        "compression_factor": 1.0,
        "entropy_norm": 0.6257817858666852,
        "quantiles": {
          "min": 0,
          "q10": 460,
          "q25": 465,
          "q75": 480,
          "q90": 491,
          "max": 511
        }
      },
      "decision": {
        "label": "keep",
        "reasons": [
          "metrics_within_thresholds"
        ],
        "thresholds": {
          "preserve_threshold": 0.95,
          "compression_threshold": 8.0,
          "entropy_threshold": 0.75,
          "entropy_trigger_requires_raw_unique_gt_K": true
        }
      }
    },
    {
      "feature": "callbacks.ncallbacks",
      "n": 46876,
      "K": 512,
      "effective_num_bins": 512,
      "raw": {
        "train_min": 50.0,
        "train_max": 89.0,
        "train_range": 39.0,
        "num_unique": 13,
        "zero_ratio": 0.0,
        "is_constant": false
      },
      "token": {
        "num_tokens_used": 13,
        "bins_used": 13,
        "possible_unique": 13,
        "preserve_ratio": 1.0,
        "unique_preserve_ratio": 1.0,
        "compression_factor": 1.0,
        "entropy_norm": 0.44011199341681984,
        "quantiles": {
          "min": 0,
          "q10": 472,
          "q25": 485,
          "q75": 498,
          "q90": 498,
          "max": 511
        }
      },
      "decision": {
        "label": "keep",
        "reasons": [
          "metrics_within_thresholds"
        ],
        "thresholds": {
          "preserve_threshold": 0.95,
          "compression_threshold": 8.0,
          "entropy_threshold": 0.75,
          "entropy_trigger_requires_raw_unique_gt_K": true
        }
      }
    },
    {
      "feature": "callbacks.nanonymous",
      "n": 46876,
      "K": 512,
      "effective_num_bins": 512,
      "raw": {
        "train_min": 0.0,
        "train_max": 1.0,
        "train_range": 1.0,
        "num_unique": 2,
        "zero_ratio": 0.9991466848707228,
        "is_constant": false
      },
      "token": {
        "num_tokens_used": 2,
        "bins_used": 2,
        "possible_unique": 2,
        "preserve_ratio": 1.0,
        "unique_preserve_ratio": 1.0,
        "compression_factor": 1.0,
        "entropy_norm": 0.009929783327334362,
        "quantiles": {
          "min": 0,
          "q10": 0,
          "q25": 0,
          "q75": 0,
          "q90": 0,
          "max": 511
        }
      },
      "decision": {
        "label": "keep",
        "reasons": [
          "metrics_within_thresholds"
        ],
        "thresholds": {
          "preserve_threshold": 0.95,
          "compression_threshold": 8.0,
          "entropy_threshold": 0.75,
          "entropy_trigger_requires_raw_unique_gt_K": true
        }
      }
    },
    {
      "feature": "callbacks.ngeneric",
      "n": 46876,
      "K": 512,
      "effective_num_bins": 512,
      "raw": {
        "train_min": 7.0,
        "train_max": 8.0,
        "train_range": 1.0,
        "num_unique": 2,
        "zero_ratio": 0.0,
        "is_constant": false
      },
      "token": {
        "num_tokens_used": 2,
        "bins_used": 2,
        "possible_unique": 2,
        "preserve_ratio": 1.0,
        "unique_preserve_ratio": 1.0,
        "compression_factor": 1.0,
        "entropy_norm": 0.0018398586124575684,
        "quantiles": {
          "min": 0,
          "q10": 511,
          "q25": 511,
          "q75": 511,
          "q90": 511,
          "max": 511
        }
      },
      "decision": {
        "label": "keep",
        "reasons": [
          "metrics_within_thresholds"
        ],
        "thresholds": {
          "preserve_threshold": 0.95,
          "compression_threshold": 8.0,
          "entropy_threshold": 0.75,
          "entropy_trigger_requires_raw_unique_gt_K": true
        }
      }
    }
  ]
}